{
"meta":{"test_sets":[],"test_metrics":[],"learn_metrics":[{"best_value":"Min","name":"Logloss"}],"launch_mode":"Train","parameters":"","iteration_count":500,"learn_sets":["learn"],"name":"experiment"},
"iterations":[
{"learn":[0.685780231],"iteration":0,"passed_time":0.00347876364,"remaining_time":1.735903057},
{"learn":[0.6790291306],"iteration":1,"passed_time":0.007009904368,"remaining_time":1.745466188},
{"learn":[0.6721460059],"iteration":2,"passed_time":0.01052550281,"remaining_time":1.743724965},
{"learn":[0.6658958932],"iteration":3,"passed_time":0.01405972699,"remaining_time":1.743406147},
{"learn":[0.6603681588],"iteration":4,"passed_time":0.01546015781,"remaining_time":1.530555623},
{"learn":[0.654392036],"iteration":5,"passed_time":0.01902425818,"remaining_time":1.56633059},
{"learn":[0.6482900623],"iteration":6,"passed_time":0.02256677436,"remaining_time":1.58934568},
{"learn":[0.6426817295],"iteration":7,"passed_time":0.02389782741,"remaining_time":1.469716386},
{"learn":[0.6372079988],"iteration":8,"passed_time":0.02762210083,"remaining_time":1.506939057},
{"learn":[0.6316874034],"iteration":9,"passed_time":0.03116599207,"remaining_time":1.527133611},
{"learn":[0.6260337582],"iteration":10,"passed_time":0.03477821936,"remaining_time":1.546049933},
{"learn":[0.6209077391],"iteration":11,"passed_time":0.03644153565,"remaining_time":1.481955783},
{"learn":[0.6157726806],"iteration":12,"passed_time":0.03819827233,"remaining_time":1.430966048},
{"learn":[0.6106214016],"iteration":13,"passed_time":0.04163565932,"remaining_time":1.445352174},
{"learn":[0.6055876135],"iteration":14,"passed_time":0.04502441937,"remaining_time":1.45578956},
{"learn":[0.6009028301],"iteration":15,"passed_time":0.0488114453,"remaining_time":1.47654622},
{"learn":[0.596287302],"iteration":16,"passed_time":0.05233350233,"remaining_time":1.486887154},
{"learn":[0.5915353891],"iteration":17,"passed_time":0.05635457925,"remaining_time":1.5090504},
{"learn":[0.5874513409],"iteration":18,"passed_time":0.06010114523,"remaining_time":1.52150794},
{"learn":[0.5833384712],"iteration":19,"passed_time":0.06375716594,"remaining_time":1.530171982},
{"learn":[0.5792234431],"iteration":20,"passed_time":0.0672858899,"remaining_time":1.534759108},
{"learn":[0.5752491705],"iteration":21,"passed_time":0.07079919658,"remaining_time":1.538273453},
{"learn":[0.5713679446],"iteration":22,"passed_time":0.07452588677,"remaining_time":1.545602087},
{"learn":[0.5674514324],"iteration":23,"passed_time":0.07805344402,"remaining_time":1.548059973},
{"learn":[0.5637922052],"iteration":24,"passed_time":0.08096931023,"remaining_time":1.538416894},
{"learn":[0.5603261643],"iteration":25,"passed_time":0.08276467345,"remaining_time":1.508863662},
{"learn":[0.5566703514],"iteration":26,"passed_time":0.08650761428,"remaining_time":1.515485243},
{"learn":[0.5529953725],"iteration":27,"passed_time":0.09000275358,"remaining_time":1.517189275},
{"learn":[0.5495430507],"iteration":28,"passed_time":0.09362793972,"remaining_time":1.520646883},
{"learn":[0.5464842575],"iteration":29,"passed_time":0.09705957648,"remaining_time":1.520600032},
{"learn":[0.5432529048],"iteration":30,"passed_time":0.1006514696,"remaining_time":1.522759331},
{"learn":[0.5398734163],"iteration":31,"passed_time":0.1044018691,"remaining_time":1.526877336},
{"learn":[0.5367992097],"iteration":32,"passed_time":0.107986387,"remaining_time":1.528170991},
{"learn":[0.534081348],"iteration":33,"passed_time":0.1097232895,"remaining_time":1.503854497},
{"learn":[0.5310774179],"iteration":34,"passed_time":0.1132917651,"remaining_time":1.505162021},
{"learn":[0.5283649725],"iteration":35,"passed_time":0.116828906,"remaining_time":1.505794789},
{"learn":[0.5255809394],"iteration":36,"passed_time":0.1203287122,"remaining_time":1.505734966},
{"learn":[0.523195176],"iteration":37,"passed_time":0.1226315956,"remaining_time":1.490942031},
{"learn":[0.5206743238],"iteration":38,"passed_time":0.1262533233,"remaining_time":1.492379027},
{"learn":[0.5181017051],"iteration":39,"passed_time":0.1297854641,"remaining_time":1.492532837},
{"learn":[0.515662952],"iteration":40,"passed_time":0.1320961811,"remaining_time":1.478832857},
{"learn":[0.5131487216],"iteration":41,"passed_time":0.1356707403,"remaining_time":1.47945712},
{"learn":[0.5107901394],"iteration":42,"passed_time":0.1394126811,"remaining_time":1.481665006},
{"learn":[0.5086499868],"iteration":43,"passed_time":0.1429084037,"remaining_time":1.481050729},
{"learn":[0.5062651632],"iteration":44,"passed_time":0.1466363439,"remaining_time":1.482656367},
{"learn":[0.5040481222],"iteration":45,"passed_time":0.1502304038,"remaining_time":1.482708768},
{"learn":[0.5020970503],"iteration":46,"passed_time":0.1526884185,"remaining_time":1.471656459},
{"learn":[0.5000074483],"iteration":47,"passed_time":0.1562299346,"remaining_time":1.471165218},
{"learn":[0.498238986],"iteration":48,"passed_time":0.159861496,"remaining_time":1.471378259},
{"learn":[0.496130674],"iteration":49,"passed_time":0.1634472223,"remaining_time":1.471025},
{"learn":[0.4942647391],"iteration":50,"passed_time":0.1669447783,"remaining_time":1.469768735},
{"learn":[0.4923243879],"iteration":51,"passed_time":0.1705344214,"remaining_time":1.46921963},
{"learn":[0.4904459437],"iteration":52,"passed_time":0.174172733,"remaining_time":1.468966258},
{"learn":[0.4888074984],"iteration":53,"passed_time":0.1765039093,"remaining_time":1.457791547},
{"learn":[0.4870262052],"iteration":54,"passed_time":0.180136179,"remaining_time":1.457465449},
{"learn":[0.4853203815],"iteration":55,"passed_time":0.1838126589,"remaining_time":1.457371795},
{"learn":[0.4836189447],"iteration":56,"passed_time":0.1873714674,"remaining_time":1.456237896},
{"learn":[0.481954284],"iteration":57,"passed_time":0.1909713608,"remaining_time":1.455333474},
{"learn":[0.4802385018],"iteration":58,"passed_time":0.1946798003,"remaining_time":1.455149016},
{"learn":[0.478971899],"iteration":59,"passed_time":0.1982720268,"remaining_time":1.453994863},
{"learn":[0.4774587176],"iteration":60,"passed_time":0.2018582531,"remaining_time":1.452717592},
{"learn":[0.4763876973],"iteration":61,"passed_time":0.2030731348,"remaining_time":1.434613436},
{"learn":[0.4750002268],"iteration":62,"passed_time":0.2053907272,"remaining_time":1.424694409},
{"learn":[0.4735521412],"iteration":63,"passed_time":0.2087559863,"remaining_time":1.422150157},
{"learn":[0.4723540322],"iteration":64,"passed_time":0.2122072488,"remaining_time":1.420156204},
{"learn":[0.471254035],"iteration":65,"passed_time":0.2137180174,"remaining_time":1.405357872},
{"learn":[0.47004497],"iteration":66,"passed_time":0.2151636167,"remaining_time":1.390535015},
{"learn":[0.468689474],"iteration":67,"passed_time":0.2187007993,"remaining_time":1.389393313},
{"learn":[0.4672456377],"iteration":68,"passed_time":0.2224688245,"remaining_time":1.389624106},
{"learn":[0.4663074036],"iteration":69,"passed_time":0.2236974151,"remaining_time":1.374141264},
{"learn":[0.4649651843],"iteration":70,"passed_time":0.2274838577,"remaining_time":1.37451514},
{"learn":[0.4637128245],"iteration":71,"passed_time":0.2309759968,"remaining_time":1.373023981},
{"learn":[0.4625587272],"iteration":72,"passed_time":0.2346878114,"remaining_time":1.372762952},
{"learn":[0.4620182573],"iteration":73,"passed_time":0.2356413078,"remaining_time":1.356529691},
{"learn":[0.4609938274],"iteration":74,"passed_time":0.2391146128,"remaining_time":1.354982806},
{"learn":[0.4598935731],"iteration":75,"passed_time":0.2424776219,"remaining_time":1.35276989},
{"learn":[0.4588749981],"iteration":76,"passed_time":0.2461813111,"remaining_time":1.352398631},
{"learn":[0.4577522237],"iteration":77,"passed_time":0.2496421574,"remaining_time":1.350628082},
{"learn":[0.4566151478],"iteration":78,"passed_time":0.2531600476,"remaining_time":1.349118735},
{"learn":[0.4556721797],"iteration":79,"passed_time":0.2567519824,"remaining_time":1.347947908},
{"learn":[0.4546997354],"iteration":80,"passed_time":0.2602285793,"remaining_time":1.346120676},
{"learn":[0.4536271426],"iteration":81,"passed_time":0.2637921797,"remaining_time":1.344696721},
{"learn":[0.4529858804],"iteration":82,"passed_time":0.2650501465,"remaining_time":1.331637483},
{"learn":[0.4523875852],"iteration":83,"passed_time":0.2661049385,"remaining_time":1.317853029},
{"learn":[0.451515714],"iteration":84,"passed_time":0.2678550916,"remaining_time":1.307763094},
{"learn":[0.4506005979],"iteration":85,"passed_time":0.2714865696,"remaining_time":1.306923719},
{"learn":[0.449707438],"iteration":86,"passed_time":0.2749106228,"remaining_time":1.305035485},
{"learn":[0.4487801086],"iteration":87,"passed_time":0.2785218917,"remaining_time":1.303988857},
{"learn":[0.447992917],"iteration":88,"passed_time":0.2820244063,"remaining_time":1.302382371},
{"learn":[0.4473514585],"iteration":89,"passed_time":0.2837106818,"remaining_time":1.292459773},
{"learn":[0.4465587013],"iteration":90,"passed_time":0.2872644484,"remaining_time":1.291111642},
{"learn":[0.4457073913],"iteration":91,"passed_time":0.2907609211,"remaining_time":1.289461476},
{"learn":[0.4449440531],"iteration":92,"passed_time":0.2942337679,"remaining_time":1.28766821},
{"learn":[0.4440916763],"iteration":93,"passed_time":0.2978320363,"remaining_time":1.286380923},
{"learn":[0.4432996717],"iteration":94,"passed_time":0.3015461426,"remaining_time":1.285538819},
{"learn":[0.4424364123],"iteration":95,"passed_time":0.3051914546,"remaining_time":1.284347371},
{"learn":[0.441606165],"iteration":96,"passed_time":0.3088384332,"remaining_time":1.283112254},
{"learn":[0.4407610433],"iteration":97,"passed_time":0.3124724114,"remaining_time":1.281774586},
{"learn":[0.440433815],"iteration":98,"passed_time":0.3134947855,"remaining_time":1.269812212},
{"learn":[0.4399216068],"iteration":99,"passed_time":0.3149698859,"remaining_time":1.259879544},
{"learn":[0.4391623082],"iteration":100,"passed_time":0.3185229025,"remaining_time":1.25832315},
{"learn":[0.438480977],"iteration":101,"passed_time":0.3220680438,"remaining_time":1.256696877},
{"learn":[0.4381540044],"iteration":102,"passed_time":0.3231335863,"remaining_time":1.245476056},
{"learn":[0.4373582336],"iteration":103,"passed_time":0.3267106455,"remaining_time":1.244013612},
{"learn":[0.4367021092],"iteration":104,"passed_time":0.3302779127,"remaining_time":1.242474052},
{"learn":[0.4363283715],"iteration":105,"passed_time":0.3312964116,"remaining_time":1.231422511},
{"learn":[0.4358598617],"iteration":106,"passed_time":0.3336460469,"remaining_time":1.22544763},
{"learn":[0.4352569606],"iteration":107,"passed_time":0.3371755626,"remaining_time":1.223822412},
{"learn":[0.4344901561],"iteration":108,"passed_time":0.3406181998,"remaining_time":1.221850607},
{"learn":[0.433863957],"iteration":109,"passed_time":0.3439925426,"remaining_time":1.219609924},
{"learn":[0.4331062659],"iteration":110,"passed_time":0.3477001903,"remaining_time":1.218516883},
{"learn":[0.4324384942],"iteration":111,"passed_time":0.3511409941,"remaining_time":1.21645273},
{"learn":[0.4318524976],"iteration":112,"passed_time":0.3545026698,"remaining_time":1.214093214},
{"learn":[0.4312762878],"iteration":113,"passed_time":0.3581117303,"remaining_time":1.212553753},
{"learn":[0.4307839219],"iteration":114,"passed_time":0.3616540798,"remaining_time":1.210754963},
{"learn":[0.4302601255],"iteration":115,"passed_time":0.3651007171,"remaining_time":1.208609271},
{"learn":[0.429505613],"iteration":116,"passed_time":0.368417141,"remaining_time":1.206015085},
{"learn":[0.428952277],"iteration":117,"passed_time":0.3718864042,"remaining_time":1.203903444},
{"learn":[0.4287064305],"iteration":118,"passed_time":0.3731545798,"remaining_time":1.194721806},
{"learn":[0.428467832],"iteration":119,"passed_time":0.3741327854,"remaining_time":1.184753821},
{"learn":[0.4281735795],"iteration":120,"passed_time":0.3753467922,"remaining_time":1.17567301},
{"learn":[0.4277062839],"iteration":121,"passed_time":0.3789005171,"remaining_time":1.173970455},
{"learn":[0.4275125863],"iteration":122,"passed_time":0.3799906856,"remaining_time":1.164686898},
{"learn":[0.4269342076],"iteration":123,"passed_time":0.3834455316,"remaining_time":1.162705805},
{"learn":[0.4264581249],"iteration":124,"passed_time":0.387035383,"remaining_time":1.161106149},
{"learn":[0.42603779],"iteration":125,"passed_time":0.3892390541,"remaining_time":1.155360367},
{"learn":[0.4256185928],"iteration":126,"passed_time":0.392763903,"remaining_time":1.153550676},
{"learn":[0.4250878618],"iteration":127,"passed_time":0.3966184732,"remaining_time":1.152672438},
{"learn":[0.424519838],"iteration":128,"passed_time":0.4001875321,"remaining_time":1.150926934},
{"learn":[0.4241158716],"iteration":129,"passed_time":0.4036433782,"remaining_time":1.148831153},
{"learn":[0.4236994781],"iteration":130,"passed_time":0.407108308,"remaining_time":1.146740196},
{"learn":[0.4231229161],"iteration":131,"passed_time":0.4107097015,"remaining_time":1.145008865},
{"learn":[0.4226279552],"iteration":132,"passed_time":0.4140818359,"remaining_time":1.142616795},
{"learn":[0.4220465409],"iteration":133,"passed_time":0.4176411861,"remaining_time":1.140721448},
{"learn":[0.421544847],"iteration":134,"passed_time":0.4211910775,"remaining_time":1.138775876},
{"learn":[0.4210797045],"iteration":135,"passed_time":0.4249692698,"remaining_time":1.137417751},
{"learn":[0.4206207013],"iteration":136,"passed_time":0.4286756675,"remaining_time":1.135834068},
{"learn":[0.42023208],"iteration":137,"passed_time":0.4322697691,"remaining_time":1.133925046},
{"learn":[0.4198546676],"iteration":138,"passed_time":0.4357979097,"remaining_time":1.13182047},
{"learn":[0.4195747988],"iteration":139,"passed_time":0.4393493012,"remaining_time":1.129755346},
{"learn":[0.4192042991],"iteration":140,"passed_time":0.4427849798,"remaining_time":1.127374523},
{"learn":[0.4187348268],"iteration":141,"passed_time":0.4463844566,"remaining_time":1.125391799},
{"learn":[0.4184323971],"iteration":142,"passed_time":0.4486580472,"remaining_time":1.120076384},
{"learn":[0.4179418327],"iteration":143,"passed_time":0.4521609368,"remaining_time":1.117842316},
{"learn":[0.417427529],"iteration":144,"passed_time":0.4556989945,"remaining_time":1.115676849},
{"learn":[0.4170360635],"iteration":145,"passed_time":0.4593004297,"remaining_time":1.113646247},
{"learn":[0.416857887],"iteration":146,"passed_time":0.4608779509,"remaining_time":1.106734127},
{"learn":[0.4166601251],"iteration":147,"passed_time":0.4623313838,"remaining_time":1.099598967},
{"learn":[0.4162632431],"iteration":148,"passed_time":0.4658618161,"remaining_time":1.097432869},
{"learn":[0.415963945],"iteration":149,"passed_time":0.4692063661,"remaining_time":1.094814854},
{"learn":[0.4155701854],"iteration":150,"passed_time":0.4729704745,"remaining_time":1.093156924},
{"learn":[0.4152063465],"iteration":151,"passed_time":0.4766742054,"remaining_time":1.091333049},
{"learn":[0.4149749305],"iteration":152,"passed_time":0.4778422103,"remaining_time":1.08373364},
{"learn":[0.4144779325],"iteration":153,"passed_time":0.4815528998,"remaining_time":1.081930541},
{"learn":[0.4140989863],"iteration":154,"passed_time":0.4850498309,"remaining_time":1.079627043},
{"learn":[0.4137606726],"iteration":155,"passed_time":0.4886882259,"remaining_time":1.07762019},
{"learn":[0.4134131584],"iteration":156,"passed_time":0.4921514055,"remaining_time":1.075209759},
{"learn":[0.4130686083],"iteration":157,"passed_time":0.4958861377,"remaining_time":1.073373792},
{"learn":[0.4126962262],"iteration":158,"passed_time":0.4993205246,"remaining_time":1.070869804},
{"learn":[0.4125831541],"iteration":159,"passed_time":0.5003395652,"remaining_time":1.063221576},
{"learn":[0.4122339465],"iteration":160,"passed_time":0.5040580884,"remaining_time":1.061339702},
{"learn":[0.4118516469],"iteration":161,"passed_time":0.507787862,"remaining_time":1.059458626},
{"learn":[0.4114391086],"iteration":162,"passed_time":0.5114952181,"remaining_time":1.057508518},
{"learn":[0.4110110972],"iteration":163,"passed_time":0.5150492348,"remaining_time":1.055222822},
{"learn":[0.4108357151],"iteration":164,"passed_time":0.5165330856,"remaining_time":1.048718689},
{"learn":[0.4103537536],"iteration":165,"passed_time":0.520398948,"remaining_time":1.047067763},
{"learn":[0.4099126956],"iteration":166,"passed_time":0.524012342,"remaining_time":1.044886885},
{"learn":[0.4095903201],"iteration":167,"passed_time":0.5274894389,"remaining_time":1.042419605},
{"learn":[0.4093201475],"iteration":168,"passed_time":0.5311582934,"remaining_time":1.040315947},
{"learn":[0.4092474853],"iteration":169,"passed_time":0.5323030891,"remaining_time":1.033294232},
{"learn":[0.4088747512],"iteration":170,"passed_time":0.535790478,"remaining_time":1.030848347},
{"learn":[0.4085547055],"iteration":171,"passed_time":0.5393890798,"remaining_time":1.028602431},
{"learn":[0.4082556482],"iteration":172,"passed_time":0.5431063529,"remaining_time":1.026565187},
{"learn":[0.4079327207],"iteration":173,"passed_time":0.5465678659,"remaining_time":1.02402945},
{"learn":[0.4076464085],"iteration":174,"passed_time":0.5501700094,"remaining_time":1.021744303},
{"learn":[0.4074196758],"iteration":175,"passed_time":0.5539348678,"remaining_time":1.019743734},
{"learn":[0.407243782],"iteration":176,"passed_time":0.556230376,"remaining_time":1.015041873},
{"learn":[0.4071127492],"iteration":177,"passed_time":0.5576553911,"remaining_time":1.008792337},
{"learn":[0.4067705749],"iteration":178,"passed_time":0.5611523638,"remaining_time":1.00631234},
{"learn":[0.4066270751],"iteration":179,"passed_time":0.5627313017,"remaining_time":1.000411203},
{"learn":[0.4063415826],"iteration":180,"passed_time":0.5662942771,"remaining_time":0.9980545546},
{"learn":[0.4060849084],"iteration":181,"passed_time":0.5697653737,"remaining_time":0.9955241145},
{"learn":[0.4058231728],"iteration":182,"passed_time":0.5735407742,"remaining_time":0.9935105214},
{"learn":[0.4054325988],"iteration":183,"passed_time":0.5771807942,"remaining_time":0.9912452771},
{"learn":[0.4050582659],"iteration":184,"passed_time":0.5806074308,"remaining_time":0.9886018417},
{"learn":[0.4047179195],"iteration":185,"passed_time":0.5841296962,"remaining_time":0.9861114226},
{"learn":[0.4044847442],"iteration":186,"passed_time":0.5875706667,"remaining_time":0.9834738966},
{"learn":[0.4041085418],"iteration":187,"passed_time":0.5910503887,"remaining_time":0.9808921344},
{"learn":[0.4038052361],"iteration":188,"passed_time":0.5946317397,"remaining_time":0.9784681008},
{"learn":[0.4035097538],"iteration":189,"passed_time":0.5983394292,"remaining_time":0.976238016},
{"learn":[0.403436182],"iteration":190,"passed_time":0.5995143927,"remaining_time":0.9698950122},
{"learn":[0.4031833189],"iteration":191,"passed_time":0.6030863683,"remaining_time":0.9674510492},
{"learn":[0.402914575],"iteration":192,"passed_time":0.6065806326,"remaining_time":0.9648717835},
{"learn":[0.4026484119],"iteration":193,"passed_time":0.6101223987,"remaining_time":0.9623580104},
{"learn":[0.402369761],"iteration":194,"passed_time":0.6137387512,"remaining_time":0.9599503544},
{"learn":[0.4021715985],"iteration":195,"passed_time":0.6171864303,"remaining_time":0.957268749},
{"learn":[0.401792005],"iteration":196,"passed_time":0.6206284008,"remaining_time":0.954570586},
{"learn":[0.4015438039],"iteration":197,"passed_time":0.62441376,"remaining_time":0.9523886642},
{"learn":[0.4015140336],"iteration":198,"passed_time":0.6253160043,"remaining_time":0.9458297351},
{"learn":[0.4013133457],"iteration":199,"passed_time":0.6289145643,"remaining_time":0.9433718465},
{"learn":[0.4010792939],"iteration":200,"passed_time":0.6326163785,"remaining_time":0.9410562049},
{"learn":[0.4007742289],"iteration":201,"passed_time":0.6360180558,"remaining_time":0.9382840625},
{"learn":[0.4005493662],"iteration":202,"passed_time":0.639410566,"remaining_time":0.9354923059},
{"learn":[0.4003688392],"iteration":203,"passed_time":0.6430089594,"remaining_time":0.9329933921},
{"learn":[0.4001033386],"iteration":204,"passed_time":0.6464970567,"remaining_time":0.9303250329},
{"learn":[0.3998397693],"iteration":205,"passed_time":0.6500755743,"remaining_time":0.9277777615},
{"learn":[0.3995655786],"iteration":206,"passed_time":0.6538751008,"remaining_time":0.9255333552},
{"learn":[0.3993401196],"iteration":207,"passed_time":0.6575498306,"remaining_time":0.9230988006},
{"learn":[0.3991042292],"iteration":208,"passed_time":0.6612136849,"remaining_time":0.9206372359},
{"learn":[0.398847137],"iteration":209,"passed_time":0.6649090822,"remaining_time":0.9182077802},
{"learn":[0.3985972922],"iteration":210,"passed_time":0.6684376395,"remaining_time":0.9155378095},
{"learn":[0.3983328423],"iteration":211,"passed_time":0.6720381996,"remaining_time":0.9129575542},
{"learn":[0.3981782373],"iteration":212,"passed_time":0.6756962621,"remaining_time":0.9104451982},
{"learn":[0.3978915203],"iteration":213,"passed_time":0.6791013978,"remaining_time":0.9075841111},
{"learn":[0.3975938592],"iteration":214,"passed_time":0.6827973784,"remaining_time":0.9051035016},
{"learn":[0.3972535193],"iteration":215,"passed_time":0.6862175147,"remaining_time":0.9022489545},
{"learn":[0.3970870266],"iteration":216,"passed_time":0.6895812738,"remaining_time":0.8993156704},
{"learn":[0.3969045328],"iteration":217,"passed_time":0.6930892053,"remaining_time":0.8965649352},
{"learn":[0.3966725426],"iteration":218,"passed_time":0.6965700523,"remaining_time":0.8937725329},
{"learn":[0.39645395],"iteration":219,"passed_time":0.7000663583,"remaining_time":0.8909935469},
{"learn":[0.3961821044],"iteration":220,"passed_time":0.7036408341,"remaining_time":0.8883067544},
{"learn":[0.3959880702],"iteration":221,"passed_time":0.7070942634,"remaining_time":0.8854603839},
{"learn":[0.3958326854],"iteration":222,"passed_time":0.7107185745,"remaining_time":0.8828208302},
{"learn":[0.3955081239],"iteration":223,"passed_time":0.714184171,"remaining_time":0.8799769249},
{"learn":[0.3952134493],"iteration":224,"passed_time":0.7178636926,"remaining_time":0.8773889576},
{"learn":[0.3950720506],"iteration":225,"passed_time":0.7213832079,"remaining_time":0.8745973405},
{"learn":[0.3949506933],"iteration":226,"passed_time":0.7229696461,"remaining_time":0.8694745083},
{"learn":[0.3946534977],"iteration":227,"passed_time":0.7266385006,"remaining_time":0.8668669832},
{"learn":[0.3942805825],"iteration":228,"passed_time":0.7302918129,"remaining_time":0.8642317961},
{"learn":[0.3940743416],"iteration":229,"passed_time":0.7338557883,"remaining_time":0.8614828819},
{"learn":[0.3938507799],"iteration":230,"passed_time":0.7374957667,"remaining_time":0.8588154166},
{"learn":[0.3935896974],"iteration":231,"passed_time":0.7409444458,"remaining_time":0.8559185839},
{"learn":[0.3934219098],"iteration":232,"passed_time":0.7446283009,"remaining_time":0.8532865079},
{"learn":[0.3931748633],"iteration":233,"passed_time":0.7483173646,"remaining_time":0.8506513632},
{"learn":[0.3929792764],"iteration":234,"passed_time":0.7519122162,"remaining_time":0.8479010098},
{"learn":[0.3927844841],"iteration":235,"passed_time":0.7553811461,"remaining_time":0.845002638},
{"learn":[0.3926015075],"iteration":236,"passed_time":0.7588227,"remaining_time":0.8420690721},
{"learn":[0.3924632473],"iteration":237,"passed_time":0.7625442233,"remaining_time":0.8394394391},
{"learn":[0.392301081],"iteration":238,"passed_time":0.7660932814,"remaining_time":0.8366123282},
{"learn":[0.392123237],"iteration":239,"passed_time":0.7696770909,"remaining_time":0.8338168484},
{"learn":[0.3920927723],"iteration":240,"passed_time":0.77057496,"remaining_time":0.8281282765},
{"learn":[0.3918401402],"iteration":241,"passed_time":0.7739590115,"remaining_time":0.8251298553},
{"learn":[0.3916575442],"iteration":242,"passed_time":0.7774329416,"remaining_time":0.8222233169},
{"learn":[0.3912532836],"iteration":243,"passed_time":0.7810387103,"remaining_time":0.8194504502},
{"learn":[0.391003023],"iteration":244,"passed_time":0.7846654382,"remaining_time":0.8166925989},
{"learn":[0.3908106376],"iteration":245,"passed_time":0.788089533,"remaining_time":0.8137184609},
{"learn":[0.3906075527],"iteration":246,"passed_time":0.7916581336,"remaining_time":0.8108886955},
{"learn":[0.3904253319],"iteration":247,"passed_time":0.7953099041,"remaining_time":0.8081374832},
{"learn":[0.3900494314],"iteration":248,"passed_time":0.7990926798,"remaining_time":0.8055110949},
{"learn":[0.3897221729],"iteration":249,"passed_time":0.8027226995,"remaining_time":0.8027226995},
{"learn":[0.3895592717],"iteration":250,"passed_time":0.8061236684,"remaining_time":0.7997003722},
{"learn":[0.3893896735],"iteration":251,"passed_time":0.8097798141,"remaining_time":0.7969261663},
{"learn":[0.3892239973],"iteration":252,"passed_time":0.8134785865,"remaining_time":0.7941866042},
{"learn":[0.3890586645],"iteration":253,"passed_time":0.8170122273,"remaining_time":0.7912795588},
{"learn":[0.3887344253],"iteration":254,"passed_time":0.8204871575,"remaining_time":0.7883111905},
{"learn":[0.3885486932],"iteration":255,"passed_time":0.8238551667,"remaining_time":0.7852369558},
{"learn":[0.388297974],"iteration":256,"passed_time":0.8276746106,"remaining_time":0.7825872777},
{"learn":[0.3881296],"iteration":257,"passed_time":0.8311599578,"remaining_time":0.7796151542},
{"learn":[0.388003881],"iteration":258,"passed_time":0.8347604763,"remaining_time":0.7767462347},
{"learn":[0.3879508298],"iteration":259,"passed_time":0.8361546986,"remaining_time":0.7718351064},
{"learn":[0.3878835972],"iteration":260,"passed_time":0.8378211816,"remaining_time":0.7672002391},
{"learn":[0.38766016],"iteration":261,"passed_time":0.8413811152,"remaining_time":0.7643080359},
{"learn":[0.3874924927],"iteration":262,"passed_time":0.8449871756,"remaining_time":0.7614523217},
{"learn":[0.3874682321],"iteration":263,"passed_time":0.8462314335,"remaining_time":0.7564796148},
{"learn":[0.3873555625],"iteration":264,"passed_time":0.8500521274,"remaining_time":0.7538198111},
{"learn":[0.3871680376],"iteration":265,"passed_time":0.8534475961,"remaining_time":0.7507772086},
{"learn":[0.3869376213],"iteration":266,"passed_time":0.8568734826,"remaining_time":0.7477585073},
{"learn":[0.3867020781],"iteration":267,"passed_time":0.8607279279,"remaining_time":0.7451077585},
{"learn":[0.3864128844],"iteration":268,"passed_time":0.8641337303,"remaining_time":0.7420627944},
{"learn":[0.3862073264],"iteration":269,"passed_time":0.8675520748,"remaining_time":0.7390258415},
{"learn":[0.3861950132],"iteration":270,"passed_time":0.8685538231,"remaining_time":0.7339440055},
{"learn":[0.3859209896],"iteration":271,"passed_time":0.8719932518,"remaining_time":0.7309355199},
{"learn":[0.3857756629],"iteration":272,"passed_time":0.8755728112,"remaining_time":0.7280403961},
{"learn":[0.385603634],"iteration":273,"passed_time":0.879031199,"remaining_time":0.725040332},
{"learn":[0.3853118181],"iteration":274,"passed_time":0.8823863744,"remaining_time":0.7219524881},
{"learn":[0.3851475163],"iteration":275,"passed_time":0.8858074274,"remaining_time":0.7189161729},
{"learn":[0.3849562369],"iteration":276,"passed_time":0.8894130711,"remaining_time":0.7160256854},
{"learn":[0.3848786983],"iteration":277,"passed_time":0.891283729,"remaining_time":0.7117445605},
{"learn":[0.384708683],"iteration":278,"passed_time":0.8948993731,"remaining_time":0.7088629443},
{"learn":[0.3844709497],"iteration":279,"passed_time":0.8982958418,"remaining_time":0.7058038757},
{"learn":[0.384345105],"iteration":280,"passed_time":0.9018358578,"remaining_time":0.7028542807},
{"learn":[0.3841571972],"iteration":281,"passed_time":0.9053415809,"remaining_time":0.6998739881},
{"learn":[0.383818055],"iteration":282,"passed_time":0.908907223,"remaining_time":0.6969359272},
{"learn":[0.383658205],"iteration":283,"passed_time":0.913138975,"remaining_time":0.6945000655},
{"learn":[0.3835396003],"iteration":284,"passed_time":0.9165310268,"remaining_time":0.691418143},
{"learn":[0.3833055392],"iteration":285,"passed_time":0.9201842974,"remaining_time":0.6885295093},
{"learn":[0.3831634873],"iteration":286,"passed_time":0.9238086919,"remaining_time":0.6856141163},
{"learn":[0.3828359536],"iteration":287,"passed_time":0.9272953308,"remaining_time":0.6825923963},
{"learn":[0.3826135259],"iteration":288,"passed_time":0.9310456469,"remaining_time":0.6797599706},
{"learn":[0.3824698358],"iteration":289,"passed_time":0.9346570409,"remaining_time":0.6768206158},
{"learn":[0.3821790853],"iteration":290,"passed_time":0.9382410587,"remaining_time":0.6738569803},
{"learn":[0.3819999179],"iteration":291,"passed_time":0.9417808248,"remaining_time":0.6708575738},
{"learn":[0.381867529],"iteration":292,"passed_time":0.9452605051,"remaining_time":0.6678120292},
{"learn":[0.3818567224],"iteration":293,"passed_time":0.9460827046,"remaining_time":0.6629014869},
{"learn":[0.3816039674],"iteration":294,"passed_time":0.9497752267,"remaining_time":0.6600132931},
{"learn":[0.3813783235],"iteration":295,"passed_time":0.9533942876,"remaining_time":0.6570690361},
{"learn":[0.3813672309],"iteration":296,"passed_time":0.9543209912,"remaining_time":0.6522800041},
{"learn":[0.3810770237],"iteration":297,"passed_time":0.9577331689,"remaining_time":0.6492016782},
{"learn":[0.3808611369],"iteration":298,"passed_time":0.9610817607,"remaining_time":0.6460783742},
{"learn":[0.380594637],"iteration":299,"passed_time":0.964578775,"remaining_time":0.6430525167},
{"learn":[0.3804007225],"iteration":300,"passed_time":0.9679771188,"remaining_time":0.6399582945},
{"learn":[0.3803569435],"iteration":301,"passed_time":0.9698811947,"remaining_time":0.6358823727},
{"learn":[0.3802543895],"iteration":302,"passed_time":0.9736056348,"remaining_time":0.6330043236},
{"learn":[0.380124582],"iteration":303,"passed_time":0.9771932361,"remaining_time":0.6300324812},
{"learn":[0.380017162],"iteration":304,"passed_time":0.9806154141,"remaining_time":0.6269508385},
{"learn":[0.3799118617],"iteration":305,"passed_time":0.9842075573,"remaining_time":0.6239747259},
{"learn":[0.3796546678],"iteration":306,"passed_time":0.9877758245,"remaining_time":0.62097959},
{"learn":[0.3794977648],"iteration":307,"passed_time":0.9913891352,"remaining_time":0.6180088115},
{"learn":[0.3794580618],"iteration":308,"passed_time":0.9928046499,"remaining_time":0.6136753661},
{"learn":[0.3792434761],"iteration":309,"passed_time":0.99648788,"remaining_time":0.6107506362},
{"learn":[0.3789844326],"iteration":310,"passed_time":0.9998056373,"remaining_time":0.6075989243},
{"learn":[0.3789209233],"iteration":311,"passed_time":1.002126396,"remaining_time":0.6038453927},
{"learn":[0.3786326429],"iteration":312,"passed_time":1.005502531,"remaining_time":0.6007315441},
{"learn":[0.3784776895],"iteration":313,"passed_time":1.009356976,"remaining_time":0.5978993554},
{"learn":[0.3783561842],"iteration":314,"passed_time":1.012978829,"remaining_time":0.5949240741},
{"learn":[0.378136648],"iteration":315,"passed_time":1.016490886,"remaining_time":0.5918807688},
{"learn":[0.3779800219],"iteration":316,"passed_time":1.019953024,"remaining_time":0.5888056887},
{"learn":[0.37789974],"iteration":317,"passed_time":1.021243992,"remaining_time":0.584485555},
{"learn":[0.3777624307],"iteration":318,"passed_time":1.024806884,"remaining_time":0.5814734982},
{"learn":[0.3776266289],"iteration":319,"passed_time":1.028409777,"remaining_time":0.5784804997},
{"learn":[0.3775104892],"iteration":320,"passed_time":1.031768619,"remaining_time":0.5753476102},
{"learn":[0.377331665],"iteration":321,"passed_time":1.035226674,"remaining_time":0.5722681614},
{"learn":[0.3772602435],"iteration":322,"passed_time":1.037432762,"remaining_time":0.568500306},
{"learn":[0.3770148795],"iteration":323,"passed_time":1.041289791,"remaining_time":0.5656388986},
{"learn":[0.3768561885],"iteration":324,"passed_time":1.044783013,"remaining_time":0.5625754686},
{"learn":[0.3767436535],"iteration":325,"passed_time":1.048213358,"remaining_time":0.5594758415},
{"learn":[0.376604801],"iteration":326,"passed_time":1.051853295,"remaining_time":0.5564850765},
{"learn":[0.3763983858],"iteration":327,"passed_time":1.055711449,"remaining_time":0.553604784},
{"learn":[0.3763070398],"iteration":328,"passed_time":1.05984453,"remaining_time":0.5508614426},
{"learn":[0.3761726108],"iteration":329,"passed_time":1.063384754,"remaining_time":0.5478042674},
{"learn":[0.3760737246],"iteration":330,"passed_time":1.066767139,"remaining_time":0.5446635847},
{"learn":[0.3758407681],"iteration":331,"passed_time":1.070303238,"remaining_time":0.5415992291},
{"learn":[0.3756508292],"iteration":332,"passed_time":1.073752334,"remaining_time":0.5384884079},
{"learn":[0.3755511404],"iteration":333,"passed_time":1.07745044,"remaining_time":0.5354993205},
{"learn":[0.3753833061],"iteration":334,"passed_time":1.081050542,"remaining_time":0.5324577295},
{"learn":[0.3752756456],"iteration":335,"passed_time":1.084479887,"remaining_time":0.5293294686},
{"learn":[0.3750826123],"iteration":336,"passed_time":1.087977485,"remaining_time":0.5262324332},
{"learn":[0.3748711407],"iteration":337,"passed_time":1.091541627,"remaining_time":0.5231649216},
{"learn":[0.3746912012],"iteration":338,"passed_time":1.095126978,"remaining_time":0.5201045529},
{"learn":[0.3746770634],"iteration":339,"passed_time":1.096124768,"remaining_time":0.51582342},
{"learn":[0.3744840309],"iteration":340,"passed_time":1.100144178,"remaining_time":0.5129704524},
{"learn":[0.3743112062],"iteration":341,"passed_time":1.103747155,"remaining_time":0.5099182761},
{"learn":[0.3741391282],"iteration":342,"passed_time":1.107328589,"remaining_time":0.5068530277},
{"learn":[0.3738417536],"iteration":343,"passed_time":1.110776018,"remaining_time":0.5037240082},
{"learn":[0.3738012035],"iteration":344,"passed_time":1.112462127,"remaining_time":0.4998018252},
{"learn":[0.3736326391],"iteration":345,"passed_time":1.116039811,"remaining_time":0.4967344825},
{"learn":[0.373488228],"iteration":346,"passed_time":1.119555035,"remaining_time":0.4936366579},
{"learn":[0.3733467841],"iteration":347,"passed_time":1.123283142,"remaining_time":0.4906294182},
{"learn":[0.3732506471],"iteration":348,"passed_time":1.126811032,"remaining_time":0.4875314208},
{"learn":[0.3731298725],"iteration":349,"passed_time":1.130372716,"remaining_time":0.4844454496},
{"learn":[0.3729289617],"iteration":350,"passed_time":1.133908148,"remaining_time":0.4813456242},
{"learn":[0.3727889912],"iteration":351,"passed_time":1.137464373,"remaining_time":0.4782520661},
{"learn":[0.3726588423],"iteration":352,"passed_time":1.141106394,"remaining_time":0.4751916143},
{"learn":[0.3725529202],"iteration":353,"passed_time":1.144606033,"remaining_time":0.4720691549},
{"learn":[0.3723986898],"iteration":354,"passed_time":1.148173009,"remaining_time":0.4689720739},
{"learn":[0.3721782541],"iteration":355,"passed_time":1.151613729,"remaining_time":0.4658212836},
{"learn":[0.3720132943],"iteration":356,"passed_time":1.154958696,"remaining_time":0.4626305139},
{"learn":[0.3719443369],"iteration":357,"passed_time":1.158562798,"remaining_time":0.4595416683},
{"learn":[0.3717823248],"iteration":358,"passed_time":1.162110564,"remaining_time":0.456427826},
{"learn":[0.3715919503],"iteration":359,"passed_time":1.165677414,"remaining_time":0.4533189945},
{"learn":[0.3715883198],"iteration":360,"passed_time":1.166790167,"remaining_time":0.4492626959},
{"learn":[0.3713978297],"iteration":361,"passed_time":1.170315308,"remaining_time":0.4461422996},
{"learn":[0.371185561],"iteration":362,"passed_time":1.173967037,"remaining_time":0.443067449},
{"learn":[0.3710447632],"iteration":363,"passed_time":1.177558596,"remaining_time":0.4399669481},
{"learn":[0.3707875713],"iteration":364,"passed_time":1.181037735,"remaining_time":0.4368221759},
{"learn":[0.3705680771],"iteration":365,"passed_time":1.184803593,"remaining_time":0.4337805506},
{"learn":[0.3703676537],"iteration":366,"passed_time":1.188580827,"remaining_time":0.4307391009},
{"learn":[0.3702674801],"iteration":367,"passed_time":1.192416063,"remaining_time":0.4277144575},
{"learn":[0.3700749067],"iteration":368,"passed_time":1.196252008,"remaining_time":0.4246856722},
{"learn":[0.3699117413],"iteration":369,"passed_time":1.199734647,"remaining_time":0.4215283894},
{"learn":[0.3698047577],"iteration":370,"passed_time":1.203270496,"remaining_time":0.4183878544},
{"learn":[0.3695778208],"iteration":371,"passed_time":1.206929684,"remaining_time":0.415287633},
{"learn":[0.3694449049],"iteration":372,"passed_time":1.210524368,"remaining_time":0.4121624525},
{"learn":[0.3693006784],"iteration":373,"passed_time":1.213990673,"remaining_time":0.4089915102},
{"learn":[0.3691918192],"iteration":374,"passed_time":1.217531981,"remaining_time":0.4058439937},
{"learn":[0.3690397123],"iteration":375,"passed_time":1.220935283,"remaining_time":0.40264887},
{"learn":[0.3689218184],"iteration":376,"passed_time":1.224561136,"remaining_time":0.3995252513},
{"learn":[0.3687524776],"iteration":377,"passed_time":1.228374455,"remaining_time":0.3964594801},
{"learn":[0.3686216834],"iteration":378,"passed_time":1.231990932,"remaining_time":0.3933269203},
{"learn":[0.3684714745],"iteration":379,"passed_time":1.235633744,"remaining_time":0.3902001297},
{"learn":[0.3682350491],"iteration":380,"passed_time":1.239222637,"remaining_time":0.3870537896},
{"learn":[0.3682152597],"iteration":381,"passed_time":1.24084716,"remaining_time":0.3832983375},
{"learn":[0.3680855415],"iteration":382,"passed_time":1.24443322,"remaining_time":0.380153229},
{"learn":[0.3679729354],"iteration":383,"passed_time":1.247890191,"remaining_time":0.3769668285},
{"learn":[0.3678387789],"iteration":384,"passed_time":1.251669133,"remaining_time":0.3738751956},
{"learn":[0.3677409283],"iteration":385,"passed_time":1.255087561,"remaining_time":0.3706735284},
{"learn":[0.3675233837],"iteration":386,"passed_time":1.258637369,"remaining_time":0.3675091026},
{"learn":[0.367380254],"iteration":387,"passed_time":1.26224418,"remaining_time":0.3643591446},
{"learn":[0.3672694686],"iteration":388,"passed_time":1.265899409,"remaining_time":0.3612206539},
{"learn":[0.3671085911],"iteration":389,"passed_time":1.269342463,"remaining_time":0.3580196689},
{"learn":[0.3669481942],"iteration":390,"passed_time":1.272933106,"remaining_time":0.3548585896},
{"learn":[0.366838004],"iteration":391,"passed_time":1.276569959,"remaining_time":0.3517080499},
{"learn":[0.3667105765],"iteration":392,"passed_time":1.280107558,"remaining_time":0.348528012},
{"learn":[0.3664809502],"iteration":393,"passed_time":1.283563071,"remaining_time":0.3453240749},
{"learn":[0.366382517],"iteration":394,"passed_time":1.286911121,"remaining_time":0.342090298},
{"learn":[0.3662952134],"iteration":395,"passed_time":1.290386426,"remaining_time":0.3388893645},
{"learn":[0.3662429831],"iteration":396,"passed_time":1.29262289,"remaining_time":0.3353656365},
{"learn":[0.3660870046],"iteration":397,"passed_time":1.296057486,"remaining_time":0.332155436},
{"learn":[0.3658897747],"iteration":398,"passed_time":1.299714048,"remaining_time":0.3290002979},
{"learn":[0.3657608688],"iteration":399,"passed_time":1.303388361,"remaining_time":0.3258470903},
{"learn":[0.3656162433],"iteration":400,"passed_time":1.30717372,"remaining_time":0.322718699},
{"learn":[0.3654987573],"iteration":401,"passed_time":1.310796573,"remaining_time":0.3195474233},
{"learn":[0.365378394],"iteration":402,"passed_time":1.3141845,"remaining_time":0.316317361},
{"learn":[0.3652688974],"iteration":403,"passed_time":1.317745267,"remaining_time":0.3131275881},
{"learn":[0.365127587],"iteration":404,"passed_time":1.321308159,"remaining_time":0.3099364816},
{"learn":[0.3649141378],"iteration":405,"passed_time":1.324754046,"remaining_time":0.306716454},
{"learn":[0.3648993568],"iteration":406,"passed_time":1.326051973,"remaining_time":0.3030045048},
{"learn":[0.3648040001],"iteration":407,"passed_time":1.329555904,"remaining_time":0.2998018215},
{"learn":[0.3646901033],"iteration":408,"passed_time":1.333171631,"remaining_time":0.296622539},
{"learn":[0.3646809148],"iteration":409,"passed_time":1.334534144,"remaining_time":0.2929465194},
{"learn":[0.3645528809],"iteration":410,"passed_time":1.338006866,"remaining_time":0.289738713},
{"learn":[0.3644119264],"iteration":411,"passed_time":1.341468004,"remaining_time":0.2865271464},
{"learn":[0.3642688704],"iteration":412,"passed_time":1.345122316,"remaining_time":0.2833550641},
{"learn":[0.3641921378],"iteration":413,"passed_time":1.348572453,"remaining_time":0.2801382391},
{"learn":[0.363961788],"iteration":414,"passed_time":1.3520438,"remaining_time":0.2769246338},
{"learn":[0.3639528346],"iteration":415,"passed_time":1.35317547,"remaining_time":0.2732373546},
{"learn":[0.3637154551],"iteration":416,"passed_time":1.356962913,"remaining_time":0.2700909395},
{"learn":[0.3636534079],"iteration":417,"passed_time":1.360380299,"remaining_time":0.2668688625},
{"learn":[0.3636434702],"iteration":418,"passed_time":1.361669975,"remaining_time":0.2632345299},
{"learn":[0.3634574596],"iteration":419,"passed_time":1.365376248,"remaining_time":0.2600716663},
{"learn":[0.3633531697],"iteration":420,"passed_time":1.369064812,"remaining_time":0.2569028982},
{"learn":[0.3632465067],"iteration":421,"passed_time":1.372760709,"remaining_time":0.2537330221},
{"learn":[0.363079613],"iteration":422,"passed_time":1.376203638,"remaining_time":0.2505146102},
{"learn":[0.3629970322],"iteration":423,"passed_time":1.379548771,"remaining_time":0.2472776099},
{"learn":[0.3629771338],"iteration":424,"passed_time":1.381236214,"remaining_time":0.2437475671},
{"learn":[0.3628646077],"iteration":425,"passed_time":1.384838149,"remaining_time":0.2405587395},
{"learn":[0.3628014219],"iteration":426,"passed_time":1.388453918,"remaining_time":0.2373703419},
{"learn":[0.3626452524],"iteration":427,"passed_time":1.392005476,"remaining_time":0.2341691455},
{"learn":[0.3626368218],"iteration":428,"passed_time":1.393132646,"remaining_time":0.2305650766},
{"learn":[0.3624967693],"iteration":429,"passed_time":1.396512447,"remaining_time":0.2273392356},
{"learn":[0.3623997899],"iteration":430,"passed_time":1.39997621,"remaining_time":0.2241261218},
{"learn":[0.3622430947],"iteration":431,"passed_time":1.40364044,"remaining_time":0.2209434026},
{"learn":[0.3619953806],"iteration":432,"passed_time":1.407515011,"remaining_time":0.2177910063},
{"learn":[0.3618572693],"iteration":433,"passed_time":1.411140864,"remaining_time":0.2145974585},
{"learn":[0.3616806497],"iteration":434,"passed_time":1.41473684,"remaining_time":0.2113974589},
{"learn":[0.361616344],"iteration":435,"passed_time":1.41832965,"remaining_time":0.208195178},
{"learn":[0.3615066311],"iteration":436,"passed_time":1.422032173,"remaining_time":0.2050069265},
{"learn":[0.3613635922],"iteration":437,"passed_time":1.42568611,"remaining_time":0.2018094494},
{"learn":[0.3612485193],"iteration":438,"passed_time":1.429162582,"remaining_time":0.1985852335},
{"learn":[0.3610766687],"iteration":439,"passed_time":1.432803352,"remaining_time":0.1953822753},
{"learn":[0.3608443503],"iteration":440,"passed_time":1.436357577,"remaining_time":0.1921657529},
{"learn":[0.3608343403],"iteration":441,"passed_time":1.43786222,"remaining_time":0.1886787529},
{"learn":[0.3606334255],"iteration":442,"passed_time":1.441459489,"remaining_time":0.1854699568},
{"learn":[0.3605225866],"iteration":443,"passed_time":1.444992963,"remaining_time":0.1822513647},
{"learn":[0.360450553],"iteration":444,"passed_time":1.448392848,"remaining_time":0.1790148464},
{"learn":[0.3602894936],"iteration":445,"passed_time":1.451816276,"remaining_time":0.175780446},
{"learn":[0.3601167264],"iteration":446,"passed_time":1.455290832,"remaining_time":0.1725512619},
{"learn":[0.3599225388],"iteration":447,"passed_time":1.459024605,"remaining_time":0.1693510703},
{"learn":[0.3597704558],"iteration":448,"passed_time":1.46298143,"remaining_time":0.1661738372},
{"learn":[0.3596986273],"iteration":449,"passed_time":1.466512279,"remaining_time":0.1629458087},
{"learn":[0.3595230863],"iteration":450,"passed_time":1.470368641,"remaining_time":0.1597518035},
{"learn":[0.3595016405],"iteration":451,"passed_time":1.471712403,"remaining_time":0.1562880428},
{"learn":[0.3594782037],"iteration":452,"passed_time":1.473499432,"remaining_time":0.152879632},
{"learn":[0.3593364556],"iteration":453,"passed_time":1.477006697,"remaining_time":0.1496526609},
{"learn":[0.3592696555],"iteration":454,"passed_time":1.480441084,"remaining_time":0.1464172501},
{"learn":[0.3591551896],"iteration":455,"passed_time":1.483855803,"remaining_time":0.1431790687},
{"learn":[0.3590774079],"iteration":456,"passed_time":1.487426362,"remaining_time":0.1399547781},
{"learn":[0.3590009038],"iteration":457,"passed_time":1.490915668,"remaining_time":0.1367215241},
{"learn":[0.3589945301],"iteration":458,"passed_time":1.492030504,"remaining_time":0.1332750559},
{"learn":[0.3589850672],"iteration":459,"passed_time":1.493293263,"remaining_time":0.1298515881},
{"learn":[0.3588240942],"iteration":460,"passed_time":1.496757442,"remaining_time":0.1266237316},
{"learn":[0.3586998259],"iteration":461,"passed_time":1.500169912,"remaining_time":0.1233905988},
{"learn":[0.3584473831],"iteration":462,"passed_time":1.503659343,"remaining_time":0.1201628416},
{"learn":[0.3583772082],"iteration":463,"passed_time":1.507234568,"remaining_time":0.1169406131},
{"learn":[0.3583045946],"iteration":464,"passed_time":1.510866838,"remaining_time":0.1137211599},
{"learn":[0.3581984487],"iteration":465,"passed_time":1.514373144,"remaining_time":0.1104907444},
{"learn":[0.35807878],"iteration":466,"passed_time":1.51815717,"remaining_time":0.1072787722},
{"learn":[0.3578875677],"iteration":467,"passed_time":1.521730646,"remaining_time":0.1040499587},
{"learn":[0.3576888881],"iteration":468,"passed_time":1.525234119,"remaining_time":0.1008150484},
{"learn":[0.3575300526],"iteration":469,"passed_time":1.528904807,"remaining_time":0.09758966853},
{"learn":[0.3574227404],"iteration":470,"passed_time":1.532671457,"remaining_time":0.09436830627},
{"learn":[0.3572752816],"iteration":471,"passed_time":1.536074176,"remaining_time":0.09112304434},
{"learn":[0.357170813],"iteration":472,"passed_time":1.539744531,"remaining_time":0.08789239393},
{"learn":[0.3570200135],"iteration":473,"passed_time":1.543135124,"remaining_time":0.08464454267},
{"learn":[0.3569366209],"iteration":474,"passed_time":1.546678599,"remaining_time":0.08140413677},
{"learn":[0.3568486378],"iteration":475,"passed_time":1.550184488,"remaining_time":0.07816056244},
{"learn":[0.356794043],"iteration":476,"passed_time":1.553736755,"remaining_time":0.07491812445},
{"learn":[0.3567714394],"iteration":477,"passed_time":1.555153853,"remaining_time":0.07157611876},
{"learn":[0.3567510777],"iteration":478,"passed_time":1.556774543,"remaining_time":0.06825107598},
{"learn":[0.3567134822],"iteration":479,"passed_time":1.560330809,"remaining_time":0.06501378372},
{"learn":[0.3565127775],"iteration":480,"passed_time":1.563842783,"remaining_time":0.06177341553},
{"learn":[0.3564275148],"iteration":481,"passed_time":1.567274336,"remaining_time":0.05852891712},
{"learn":[0.3563283873],"iteration":482,"passed_time":1.570791476,"remaining_time":0.05528665652},
{"learn":[0.3562372305],"iteration":483,"passed_time":1.574293033,"remaining_time":0.05204274488},
{"learn":[0.3562267032],"iteration":484,"passed_time":1.57601681,"remaining_time":0.04874278792},
{"learn":[0.3561575601],"iteration":485,"passed_time":1.579750125,"remaining_time":0.04550720525},
{"learn":[0.356140312],"iteration":486,"passed_time":1.581428734,"remaining_time":0.04221473005},
{"learn":[0.3561401574],"iteration":487,"passed_time":1.58256132,"remaining_time":0.0389154423},
{"learn":[0.3560707233],"iteration":488,"passed_time":1.586094753,"remaining_time":0.03567902307},
{"learn":[0.3559556445],"iteration":489,"passed_time":1.589753732,"remaining_time":0.03244395371},
{"learn":[0.3557385343],"iteration":490,"passed_time":1.59313695,"remaining_time":0.02920210296},
{"learn":[0.3556208741],"iteration":491,"passed_time":1.596850431,"remaining_time":0.02596504767},
{"learn":[0.3554586812],"iteration":492,"passed_time":1.60036578,"remaining_time":0.02272324637},
{"learn":[0.355349353],"iteration":493,"passed_time":1.603835585,"remaining_time":0.01947978443},
{"learn":[0.3552028051],"iteration":494,"passed_time":1.607242804,"remaining_time":0.0162347758},
{"learn":[0.3552025578],"iteration":495,"passed_time":1.608116547,"remaining_time":0.01296868183},
{"learn":[0.3550113121],"iteration":496,"passed_time":1.611588019,"remaining_time":0.009727895486},
{"learn":[0.3549156019],"iteration":497,"passed_time":1.61500428,"remaining_time":0.006485960964},
{"learn":[0.3547563934],"iteration":498,"passed_time":1.618426458,"remaining_time":0.003243339595},
{"learn":[0.3547084302],"iteration":499,"passed_time":1.622223443,"remaining_time":0}
]}